kossou_hillshade_base/__init__.py
kossou_hillshade_base/kossou_hillshade_base.py
kossou_hillshade_base/version.py
kossou_hillshade_base/static/n07_w006_3arc_v2.tif
kossou_hillshade_base-0.0.9.dist-info/METADATA
kossou_hillshade_base-0.0.9.dist-info/WHEEL
kossou_hillshade_base-0.0.9.dist-info/top_level.txt
kossou_hillshade_base-0.0.9.dist-info/RECORD
