Metadata-Version: 2.1
Name: kossou-hillshade-base
Version: 0.0.9
Summary: Plot hillshade over Lake Kossou using satellite elevation data
Author-email: Anthony Aylward <anthony.aylward@protonmail.com>
Project-URL: Homepage, https://https://gitlab.com/aaylward/kossou-hillshade-base
Project-URL: Documentation, https://aaylward.gitlab.io/kossou-hillshade-base
Classifier: Programming Language :: Python :: 3
Classifier: Operating System :: OS Independent
Classifier: License :: OSI Approved :: BSD License
Requires-Python: >=3.10
Requires-Dist: earthpy
Requires-Dist: matplotlib
Requires-Dist: numpy
Requires-Dist: rasterio
